mold/__init__.py
mold/__main__.py
mold/cli.py
mold/context.py
mold/asset/docs/README.md
mold/asset/docs/--version/README.md
mold/asset/docs/conf/README.md
mold/asset/docs/conf/conf_drop_help.md
mold/asset/docs/conf/conf_edit_help.md
mold/asset/docs/conf/conf_list_help.md
mold/asset/docs/conf/conf_load_help.md
mold/asset/docs/conf/conf_make_help.md
mold/asset/docs/exec/README.md
mold/asset/docs/exec/exec_drop_help.md
mold/asset/docs/exec/exec_edit_help.md
mold/asset/docs/exec/exec_list_help.md
mold/asset/docs/exec/exec_load_help.md
mold/asset/docs/exec/exec_make_help.md
mold/asset/docs/fold/README.md
mold/asset/docs/fold/fold_drop_help.md
mold/asset/docs/fold/fold_edit_help.md
mold/asset/docs/fold/fold_list_help.md
mold/asset/docs/fold/fold_load_help.md
mold/asset/docs/fold/fold_make_help.md
mold/asset/docs/leaf/README.md
mold/asset/docs/leaf/leaf_drop_help.md
mold/asset/docs/leaf/leaf_edit_help.md
mold/asset/docs/leaf/leaf_list_help.md
mold/asset/docs/leaf/leaf_load_help.md
mold/asset/docs/leaf/leaf_make_help.md
mold/asset/docs/plug/README.md
mold/asset/docs/plug/plug_drop_help.md
mold/asset/docs/plug/plug_edit_help.md
mold/asset/docs/plug/plug_list_help.md
mold/asset/docs/plug/plug_load_help.md
mold/asset/docs/plug/plug_make_help.md
mold/asset/docs/sync/README.md
mold/asset/mold_root/.gitignore
mold/asset/mold_root/README.md
mold/asset/mold_root/mold-loader.sh
mold/asset/mold_root/conf/.mold
mold/asset/mold_root/exec/.mold
mold/asset/mold_root/fold/.mold
mold/asset/mold_root/leaf/.mold
mold/asset/mold_root/plug/.mold
mold/core/__init__.py
mold/core/complete.py
mold/core/content.py
mold/core/help.py
mold/core/list.py
mold/core/sync.py
mold/core/version.py
mold/core/root/__init__.py
mold/core/root/install.py
mold/util/__init__.py
mold/util/fs.py
mold/util/git.py
mold/util/query.py
mold/util/system.py
mold_cli-0.0.2.dist-info/LICENSE.md
mold_cli-0.0.2.dist-info/METADATA
mold_cli-0.0.2.dist-info/WHEEL
mold_cli-0.0.2.dist-info/entry_points.txt
mold_cli-0.0.2.dist-info/top_level.txt
mold_cli-0.0.2.dist-info/RECORD
