Metadata-Version: 2.1
Name: mold-cli
Version: 0.0.2
Summary: mold - A CLI for system configuration and shell workflow.
Home-page: https://github.com/slugbyte/mold
Author: Duncan Marsh
Author-email: slugbyte@slugbyte.com
License: MIT
Platform: UNKNOWN
Classifier: License :: OSI Approved :: MIT License
Classifier: Programming Language :: Python
Classifier: Programming Language :: Python :: 3
Classifier: Programming Language :: Python :: 3.6
Classifier: Programming Language :: Python :: Implementation :: CPython
Classifier: Programming Language :: Python :: Implementation :: PyPy
Requires-Python: >=3.6.0
Requires-Dist: atomicwrites (==1.2.1)
Requires-Dist: attrs (==18.2.0)
Requires-Dist: bleach (==3.1.0)
Requires-Dist: certifi (==2018.11.29)
Requires-Dist: chardet (==3.0.4)
Requires-Dist: docutils (==0.14)
Requires-Dist: idna (==2.8)
Requires-Dist: Markdown (==3.0.1)
Requires-Dist: more-itertools (==5.0.0)
Requires-Dist: pkginfo (==1.5.0.1)
Requires-Dist: pluggy (==0.8.1)
Requires-Dist: py (==1.7.0)
Requires-Dist: Pygments (==2.3.1)
Requires-Dist: pytest (==4.1.1)
Requires-Dist: readme-renderer (==24.0)
Requires-Dist: requests (==2.21.0)
Requires-Dist: requests-toolbelt (==0.8.0)
Requires-Dist: six (==1.12.0)
Requires-Dist: tqdm (==4.29.1)
Requires-Dist: twine (==1.12.1)
Requires-Dist: urllib3 (==1.24.1)
Requires-Dist: webencodings (==0.5.1)
